odoo8_addon_hr_holidays_validity_date-8.0.1.0.0.99.dev5-py3.8-nspkg.pth
odoo_addons/hr_holidays_validity_date/README.rst
odoo_addons/hr_holidays_validity_date/__init__.py
odoo_addons/hr_holidays_validity_date/__openerp__.py
odoo_addons/hr_holidays_validity_date/i18n/ca.po
odoo_addons/hr_holidays_validity_date/i18n/ca_ES.po
odoo_addons/hr_holidays_validity_date/i18n/de.po
odoo_addons/hr_holidays_validity_date/i18n/es.po
odoo_addons/hr_holidays_validity_date/i18n/es_MX.po
odoo_addons/hr_holidays_validity_date/i18n/fr.po
odoo_addons/hr_holidays_validity_date/i18n/fr_CA.po
odoo_addons/hr_holidays_validity_date/i18n/hr_holidays_validity_date.pot
odoo_addons/hr_holidays_validity_date/i18n/hu.po
odoo_addons/hr_holidays_validity_date/i18n/it.po
odoo_addons/hr_holidays_validity_date/i18n/nl.po
odoo_addons/hr_holidays_validity_date/i18n/pt.po
odoo_addons/hr_holidays_validity_date/i18n/pt_BR.po
odoo_addons/hr_holidays_validity_date/i18n/ro.po
odoo_addons/hr_holidays_validity_date/i18n/sk.po
odoo_addons/hr_holidays_validity_date/i18n/sl.po
odoo_addons/hr_holidays_validity_date/i18n/zh_CN.po
odoo_addons/hr_holidays_validity_date/models/__init__.py
odoo_addons/hr_holidays_validity_date/models/hr_holidays.py
odoo_addons/hr_holidays_validity_date/static/description/icon.png
odoo_addons/hr_holidays_validity_date/tests/__init__.py
odoo_addons/hr_holidays_validity_date/tests/test_hr_holidays_validity_date.py
odoo_addons/hr_holidays_validity_date/views/hr_holidays_view.xml
odoo8_addon_hr_holidays_validity_date-8.0.1.0.0.99.dev5.dist-info/METADATA
odoo8_addon_hr_holidays_validity_date-8.0.1.0.0.99.dev5.dist-info/WHEEL
odoo8_addon_hr_holidays_validity_date-8.0.1.0.0.99.dev5.dist-info/namespace_packages.txt
odoo8_addon_hr_holidays_validity_date-8.0.1.0.0.99.dev5.dist-info/top_level.txt
odoo8_addon_hr_holidays_validity_date-8.0.1.0.0.99.dev5.dist-info/RECORD
